pipipi/__init__.py
pipipi/pipip.py
pipipi-0.1.1.dist-info/LICENSE
pipipi-0.1.1.dist-info/METADATA
pipipi-0.1.1.dist-info/WHEEL
pipipi-0.1.1.dist-info/entry_points.txt
pipipi-0.1.1.dist-info/top_level.txt
pipipi-0.1.1.dist-info/RECORD
