Metadata-Version: 2.1
Name: pipipi
Version: 0.1.1
Summary: A minimal extension of pip install with some additional functionality
Home-page: https://github.com/AmmoniumX/Pipip
Author: Diego Garcia
License: MIT
Classifier: Programming Language :: Python :: 3
Classifier: License :: OSI Approved :: MIT License
Classifier: Operating System :: OS Independent
Classifier: Programming Language :: Python :: 3.12
Classifier: Programming Language :: Python :: 3.13
License-File: LICENSE
Requires-Dist: argparse
Requires-Dist: typing
